eotds/__init__.py
eotds/hello.py
eotds-0.1.0.dist-info/WHEEL
eotds-0.1.0.dist-info/METADATA
eotds-0.1.0.dist-info/RECORD
