Metadata-Version: 2.1
Name: eotds
Version: 0.1.0
Summary: Earth Observation Training Datasets
Author: Juan Sensio
Author-email: it@earthpulse.es
Requires-Python: >=3.8,<4.0
Classifier: Programming Language :: Python :: 3
Classifier: Programming Language :: Python :: 3.8
Classifier: Programming Language :: Python :: 3.9
Classifier: Programming Language :: Python :: 3.10
